LICENSE
MANIFEST.in
README.txt
setup.py
breadcrumbs/__init__.py
breadcrumbs/models.py
breadcrumbs/tests.py
django_simple_breadcrumbs.egg-info/PKG-INFO
django_simple_breadcrumbs.egg-info/SOURCES.txt
django_simple_breadcrumbs.egg-info/dependency_links.txt
django_simple_breadcrumbs.egg-info/top_level.txt