Metadata-Version: 1.1
Name: django-simple-breadcrumbs
Version: 0.1
Summary: A simple Django app to use breadcrumbs-based navigation
Home-page: https://bitbucket.org/Mathiasdm/django-simple-breadcrumbs
Author: Andriy Drozdyuk, Mathias De Maré
Author-email: mathias.demare+breadcrumbs@gmail.com
License: BSD License
Platform: UNKNOWN
Classifier: Environment :: Web Environment
Classifier: Framework :: Django
Classifier: Intended Audience :: Developers
Classifier: License :: OSI Approved :: BSD License
Classifier: Operating System :: OS Independent
Classifier: Programming Language :: Python
Classifier: Programming Language :: Python :: 2.6
Classifier: Programming Language :: Python :: 2.7
Classifier: Topic :: Internet :: WWW/HTTP
Classifier: Topic :: Internet :: WWW/HTTP :: Dynamic Content
